Workbook
Name OLE_LINK79: 'GASTOS FOB 251120'!$A$84
Name OLE_LINK89: 'GASTOS FOB 251120'!$A$73
Name OLE_LINK93: 'GASTOS FOB 251120'!#REF!

Sheet BCN-VLC-ALG to W-E Africa
F2: EXPORT BCN/VLC/ALG > WEST/EAST AFRICA | L2: SOLICITAR BOOKING A TRAVES DE FreightSmart - E-QUOTE (AB)
F3: Europe to Africa Dry - tariff 062 | L3: RATE DATE: On board date
F4: VALIDEZ: 1 Abril 2026 hasta 30 Abril 2026 | L4: 14 free days dem/det(2in1) at POD Abidjan, Ghana, Togo, Cote d'Ivoire, 14c free days demurrages in Senegal
D6: EMERGENCY BUNKER SURCHARGE: EUR 50/20´DC & EUR 100/40´DC or HC, from 23rd.March.26
B9: Origins* | C9: Mode* | D9: Destinations* | E9: Mode* | F9: Cargo Nature* | G9: T/time (BCN/VLC) | H9: via | I9: Currency* | J9: 20'GP - DRY | K9: 40'GP - DRY | L9: 40'HQ - DRY | M9: LSA (TEU) | N9: EBS (TEU) | O9: Subject To | P9: payment Terms | Q9: Remarks
B10: BARCELONA | C10: YY | D10: Dakar, Senegal | E10: YY | F10: GC | G10: 14 | H10: Via Valencia | I10: EUR | J10: 1385 | K10: 1825 | L10: 1825 | M10: 24 | N10: 50 | O10: EBS/THC/DOC/T3/ETS | P10: ONLY PREPAID / CTN REQUIRED AT POL
B11: BARCELONA | C11: YY | D11: Abidjan, Cote d'Ivoire | E11: YY | F11: GC | G11: 23 | H11: Via Valencia | I11: EUR | J11: 1245 | K11: 1800 | L11: 1800 | M11: =M10 -> 24 | N11: =N10 -> 50 | O11: =$O$10 -> EBS/THC/DOC/T3/ETS | P11: ONLY PREPAID / CTN REQUIRED AT POL
B12: BARCELONA | C12: YY | D12: Tema, Ghana | E12: YY | F12: GC | G12: 23 | H12: Via Valencia | I12: EUR | J12: 1405 | K12: 1925 | L12: 1925 | M12: =M11 -> 24 | N12: =N11 -> 50 | O12: =$O$10 -> EBS/THC/DOC/T3/ETS | P12: ONLY PREPAID / CTN REQUIRED AT POL
B13: BARCELONA | C13: YY | D13: Lome, Togo | E13: YY | F13: GC | G13: 23 | H13: Via Valencia / Tema | I13: EUR | J13: suspendido | M13: =M10 -> 24 | N13: =N10 -> 50 | O13: =$O$10 -> EBS/THC/DOC/T3/ETS | P13: ONLY PREPAID / CTN REQUIRED AT POL | Q13: suspendido
B14: BARCELONA | C14: YY | D14: Cotonou, Benin | E14: YY | F14: GC | G14: 32 | H14: Via Valencia / Tema | I14: EUR | J14: 1950 | K14: 2650 | L14: 2650 | M14: =M13 -> 24 | N14: =N13 -> 50 | O14: =$O$10 -> EBS/THC/DOC/T3/ETS | P14: ONLY PREPAID / CTN REQUIRED AT POL
B15: VALENCIA/ALGECIRAS | C15: YY | D15: Dakar, Senegal | E15: YY | F15: GC | G15: 8 | H15: Direct | I15: EUR | J15: 870 | K15: 990 | L15: 990 | M15: =M14 -> 24 | N15: =N14 -> 50 | O15: =$O$10 -> EBS/THC/DOC/T3/ETS | P15: ONLY PREPAID / CTN REQUIRED AT POL
B16: VALENCIA/ALGECIRAS | C16: YY | D16: Tema, Ghana | E16: YY | F16: GC | G16: 20 | H16: Direct | I16: EUR | J16: 895 | K16: 1265 | L16: 1265 | M16: =M15 -> 24 | N16: =N15 -> 50 | O16: =$O$10 -> EBS/THC/DOC/T3/ETS | P16: ONLY PREPAID / CTN REQUIRED AT POL
B17: VALENCIA/ALGECIRAS | C17: YY | D17: Abidjan, Cote d'Ivoire | E17: YY | F17: GC | G17: 18 | H17: Directo | I17: EUR | J17: 720 | K17: 990 | L17: 990 | M17: =M16 -> 24 | N17: =N16 -> 50 | O17: =$O$10 -> EBS/THC/DOC/T3/ETS | P17: ONLY PREPAID / CTN REQUIRED AT POL
B18: VALENCIA/ALGECIRAS | C18: YY | D18: Lome, Togo | E18: YY | F18: GC | G18: 18 | H18: Via Tema | I18: EUR | J18: suspendido | M18: =M13 -> 24 | N18: =N13 -> 50 | O18: =$O$10 -> EBS/THC/DOC/T3/ETS | P18: ONLY PREPAID / CTN REQUIRED AT POL | Q18: suspendido
B19: VALENCIA/ALGECIRAS | C19: YY | D19: Cotonou, Benin | E19: YY | F19: GC | G19: 28 | H19: Via Tema | I19: EUR | J19: 1345 | K19: 1840 | L19: 1840 | M19: =M13 -> 24 | N19: =N13 -> 50 | O19: =$O$10 -> EBS/THC/DOC/T3/ETS | P19: ONLY PREPAID / CTN REQUIRED AT POL
B20: VALENCIA/BARCELONA/ALGECIRAS | C20: YY | D20: Mombasa, Kenya | E20: YY | F20: GC | G20: 66 | H20: Via Jebel Ali | I20: EUR | J20: 1800 | K20: 2500 | L20: 2500 | M20: =M14 -> 24 | N20: =N14 -> 50 | O20: =$O$10 -> EBS/THC/DOC/T3/ETS | P20: ONLY PREPAID / CTN REQUIRED AT POL
B21: VALENCIA/BARCELONA/ALGECIRAS | C21: YY | D21: Dar es Salaam, Tanzania | E21: YY | F21: GC | G21: 51 | H21: Via Jebel Ali | I21: EUR | J21: 1800 | K21: 2500 | L21: 2500 | M21: =M13 -> 24 | N21: =N13 -> 50 | O21: =$O$10 -> EBS/THC/DOC/T3/ETS | P21: ONLY PREPAID / CTN REQUIRED AT POL
B22: VALENCIA/BARCELONA/ALGECIRAS | C22: YY | D22: Maputo, Mozambique | E22: YY | F22: GC | G22: 74 | H22: Via Jebel Ali | I22: EUR | J22: 1800 | K22: 2500 | L22: 2500 | M22: =M13 -> 24 | N22: =N13 -> 50 | O22: =$O$10 -> EBS/THC/DOC/T3/ETS | P22: ONLY PREPAID / CTN REQUIRED AT POL
B25: REMARKS
B26: a. Fletes validos para mercancia FAK. No incluye: MARMOL(Bloque)/PIELES/SCRAPS/HIGH VALUE CARGO/SECOND HAND VEHICLES
B27: b. Fletes para Dakar, Abidjan y Tema incluyen LSA y ETS, todos incluyen CAF. Sujetos a otros gastos en origen y destino.
B28: c. DG charge of EUR 200/TEU
B29: d. LSA Eur 24x20' & EUR 48/40'
B30: e. EU ETS compliance Fee - Eur 13x20' & EUR 26/40'- PREPAID(no aplica para destinos Dakar, Abidjan y Tema)
B31: f. Sujeto a los gastos de Destino
B32: g. B/L - M/F Correction on AMS : EUR 50 / correction
B33: h. B/L Fee EUR 100/BL for manual submission, EUR 30/BL for submission (BKG&SI) through My OOCL Center
B34: i. Sujetos a VGM (VLC = Eur 10/cntr)
B35: j. Sujetos a TCM Eur 10/cntr)
B36: k. SOC surcharge: a consultar
B37: h. DG Documentation fee: Eur 40,- x ONU (maximo 3 x doc)
B38: I. Emergency Bunker Surcharge: EUR 50/20`& EUR 100/40´ from 23/March/2026 | G38: Rule Tariff Detail
B40: All surcharges and Fees shown are maximum rates and valid untill further notice (unless specified)
B41: http://www.oocl.com/eng/resourcecenter/surcharges/pages/aetsurcharges.aspx
B42: http://www.oocl.com/eng/Pages/importantnoticeforratedocument.aspx
B44: **NOTAS
B45: Resumen de los requerimientos respecto al CTN number:
B46: Embarques destino SENEGAL: obligatorio antes de la salida del barco y es motivo de baja del contenedor de listas de carga en ausencia del mismo (lo hacemos reflejar también en el BL);
B47: Embarques destino COSTA DE MARFIL: obligatorio antes de la salida del barco y es motivo de baja del contenedor de listas de carga en ausencia del mismo
B48: (lo hacemos reflejar también en el BL aunque no sería estrictamente obligatorio que se incluya en el BL);
B49: Embarques destino GHANA: no es obligatorio antes de la salida del buque aunque sí lo será antes de la llegada a destino del mismo, por lo que debe tramitarse antes de llegar. Se puede gestionar tanto en origen como en destino.
B50: No se da de baja un contenedor de lista de carga por no disponer del número antes de la salida.
B51: Excepción: en caso de tratarse de efectos personales será imprescindible el mismo antes de la salida y además tanto shipper como consignee deben ser agentes, nunca particulares.

Sheet ALG to FAR EAST
E2: EXPORT ALGECIRAS > FAR EAST (via PIRAEUS) | I2: SOLICITAR BOOKING A TRAVES DE FreightSmart - E-QUOTE (AB)
I3: RATE DATE: On board date
E4: ='BCN-VLC-ALG to W-E Africa'!F4 -> VALIDEZ: 1 Abril 2026 hasta 30 Abril 2026
D6: EMERGENCY BUNKER SURCHARGE: USD 60/20´DC & USD 120/40´DC or HC, from 23rd.March.26
B8: Origins* | C8: Destinations* | D8: Cargo Nature* | E8: via | F8: Currency* | G8: 20'GP - DRY | H8: 40'GP - DRY | I8: 40'HQ - DRY | J8: Included Charges | K8: LSA (TEU) | L8: EBS (TEU) | M8: Subject To | N8: payment Terms | O8: Remarks
B9: Algeciras | C9: Bangkok, Thailand | D9: DG;GC | E9: Piraeus / Port Klang, Selangor, Malaysia;Singapore, Singapore | F9: USD | G9: 725 | H9: 950 | I9: 950 | J9: BAF; CAF; EMS; GAS; HQA; LSA; LSS; SEC; SUZ; THC | K9: INCL | L9: 60 | M9: EBS/ETS
B10: Algeciras | C10: Belawan, Sumatera Utara, Indonesia | D10: DG;GC | E10: Piraeus / Port Klang, Selangor, Malaysia;Singapore, Singapore | F10: USD | G10: 800 | H10: 1075 | I10: 1075 | J10: BAF; CAF; EMS; GAS; HQA; LSA; LSS; SEC; SUZ; THC | K10: =K9 -> INCL | L10: =$L$10 -> 60 | M10: =$M$10 -> EBS/ETS
B11: Algeciras | C11: Busan, South Korea | D11: GC | E11: Piraeus / Ningbo;shanghai | F11: USD | G11: 545 | H11: 665 | I11: 665 | J11: BAF; CAF; EMS; GAS; HQA; LSA; LSS; SEC; SUZ; THC | K11: =K10 -> INCL | L11: =$L$10 -> 60 | M11: =$M$10 -> EBS/ETS
B12: Algeciras | C12: Changsha, Changsha, Hunan, China | D12: DG;GC | E12: Piraeus / Shanghai, China | F12: USD | G12: 825 | H12: 1150 | I12: 1150 | J12: BAF; CAF; EMS; GAS; HQA; LSA; LSS; SEC; SUZ; THC | K12: =K11 -> INCL | L12: =$L$10 -> 60 | M12: =$M$10 -> EBS/ETS
B13: Algeciras | C13: Chongqing, China | D13: DG;GC | E13: Piraeus / Shanghai, China | F13: USD | G13: 900 | H13: 1325 | I13: 1325 | J13: BAF; CAF; EMS; GAS; HQA; LSA; LSS; SEC; SUZ; THC | K13: =K12 -> INCL | L13: =$L$10 -> 60 | M13: =$M$10 -> EBS/ETS
B14: Algeciras | C14: Da Nang, Vietnam | D14: DG;GC | E14: Piraeus / Singapore, Singapore | F14: USD | G14: 1375 | H14: 2150 | I14: 2150 | J14: BAF; CAF; EMS; GAS; HQA; LSA; LSS; SEC; SUZ; THC | K14: =K13 -> INCL | L14: =$L$10 -> 60 | M14: =$M$10 -> EBS/ETS
B15: Algeciras | C15: Dalian, Dalian, Liaoning, China | D15: GC | E15: Piraeus/Singapore | F15: USD | G15: 500 | H15: 600 | I15: 600 | J15: BAF; CAF; EMS; GAS; HQA; LSA; LSS; SEC; SUZ; THC | K15: =K14 -> INCL | L15: =$L$10 -> 60 | M15: =$M$10 -> EBS/ETS
B16: Algeciras | C16: Davao City, Davao del Sur, Philippines | D16: DG;GC | E16: Piraeus / Singapore | F16: USD | G16: 1450 | H16: 2350 | I16: 2350 | J16: BAF; CAF; EMS; GAS; HQA; LSA; LSS; SEC; SUZ; THC | K16: =K15 -> INCL | L16: =$L$10 -> 60 | M16: =$M$10 -> EBS/ETS
B17: Algeciras | C17: Fuqing, Fuzhou, Fujian, China | D17: DG;GC | E17: Piraeus / Ningbo | F17: USD | G17: 725 | H17: 1000 | I17: 1000 | J17: BAF; CAF; EMS; GAS; HQA; LSA; LSS; SEC; SUZ; THC | K17: =K16 -> INCL | L17: =$L$10 -> 60 | M17: =$M$10 -> EBS/ETS
B18: Algeciras | C18: Fuzhou, Fuzhou, Fujian, China | D18: DG;GC | E18: Piraeus / Xiamen | F18: USD | G18: 700 | H18: 950 | I18: 950 | J18: BAF; CAF; EMS; GAS; HQA; LSA; LSS; SEC; SUZ; THC | K18: =K17 -> INCL | L18: =$L$10 -> 60 | M18: =$M$10 -> EBS/ETS
B19: Algeciras | C19: Guangzhou, Guangzhou, Guangdong, China | D19: DG;GC | E19: Piraeus / Hong Kong / WM1 | F19: USD | G19: 650 | H19: 900 | I19: 900 | J19: BAF; CAF; EMS; GAS; HQA; LSA; LSS; SEC; SUZ; THC | K19: =K18 -> INCL | L19: =$L$10 -> 60 | M19: =$M$10 -> EBS/ETS
B20: Algeciras | C20: Hai Phong, Vietnam | D20: DG;GC | E20: Piraeus / Singapore | F20: USD | G20: 700 | H20: 900 | I20: 900 | J20: BAF; CAF; EMS; GAS; HQA; LSA; LSS; SEC; SUZ; THC | K20: =K19 -> INCL | L20: =$L$10 -> 60 | M20: =$M$10 -> EBS/ETS
B21: Algeciras | C21: Hakata, Fukuoka, Japan | D21: DG;GC | E21: Piraeus / Kobe, Hyogo-ken, Japan | F21: USD | G21: =G28+250 -> 1100 | H21: =H28+350 -> 1400 | I21: =H21 -> 1400 | J21: BAF; CAF; EMS; GAS; HQA; LSA; LSS; SEC; SUZ; THC | K21: =K20 -> INCL | L21: =$L$10 -> 60 | M21: =$M$10 -> EBS/ETS
B22: Algeciras | C22: Ho Chi Minh, Vietnam | D22: DG;GC | E22: Piraeus / Singapore | F22: USD | G22: 650 | H22: 875 | I22: 875 | J22: BAF; CAF; EMS; GAS; HQA; LSA; LSS; SEC; SUZ; THC | K22: =K21 -> INCL | L22: =$L$10 -> 60 | M22: =$M$10 -> EBS/ETS
B23: Algeciras | C23: Hong Kong, Hong Kong | D23: GC | E23: Piraeus | F23: USD | G23: 500 | H23: 600 | I23: 600 | J23: BAF; CAF; EMS; GAS; HQA; LSA; LSS; SEC; SUZ; THC | K23: =K22 -> INCL | L23: =$L$10 -> 60 | M23: =$M$10 -> EBS/ETS
B24: Algeciras | C24: Huangpu, Guangzhou, Guangdong, China | D24: DG;GC | E24: Piraeus / Nansha;HKG | F24: USD | G24: 700 | H24: 875 | I24: 875 | J24: BAF; CAF; EMS; GAS; HQA; LSA; LSS; SEC; SUZ; THC | K24: =K23 -> INCL | L24: =$L$10 -> 60 | M24: =$M$10 -> EBS/ETS
B25: Algeciras | C25: Jakarta, Indonesia | D25: DG;GC | E25: Piraeus / Port Klang, Selangor, Malaysia;Singapore, Singapore | F25: USD | G25: 775 | H25: 1000 | I25: 1000 | J25: BAF; CAF; EMS; GAS; HQA; LSA; LSS; SEC; SUZ; THC | K25: =K24 -> INCL | L25: =$L$10 -> 60 | M25: =$M$10 -> EBS/ETS
B26: Algeciras | C26: Kaohsiung, Taiwan | D26: GC | E26: Piraeus | F26: USD | G26: 500 | H26: 600 | I26: 600 | J26: BAF; CAF; EMS; GAS; HQA; LSA; LSS; SEC; SUZ; THC | K26: =K25 -> INCL | L26: =$L$10 -> 60 | M26: =$M$10 -> EBS/ETS
B27: Algeciras | C27: Keelung, Taiwan | D27: DG;GC | E27: Piraeus / Kaohsiung, Taiwan | F27: USD | G27: 850 | H27: 950 | I27: 950 | J27: BAF; CAF; EMS; GAS; HQA; LSA; LSS; SEC; SUZ; THC | K27: =K26 -> INCL | L27: =$L$10 -> 60 | M27: =$M$10 -> EBS/ETS
B28: Algeciras | C28: Kobe, Hyogo-ken, Japan | D28: GC | E28: Piraeus / Hong Kong / WM1 | F28: USD | G28: 850 | H28: 1050 | I28: 1050 | J28: BAF; CAF; EMS; GAS; HQA; LSA; LSS; SEC; SUZ; THC | K28: =K27 -> INCL | L28: =$L$10 -> 60 | M28: =$M$10 -> EBS/ETS
B29: Algeciras | C29: Laem Chabang, Chon Buri, Thailand | D29: DG;GC | E29: Piraeus / Port Klang, Selangor, Malaysia;Singapore, Singapore | F29: USD | G29: 700 | H29: 925 | I29: 925 | J29: BAF; CAF; EMS; GAS; HQA; LSA; LSS; SEC; SUZ; THC | K29: =K28 -> INCL | L29: =$L$10 -> 60 | M29: =$M$10 -> EBS/ETS
B30: Algeciras | C30: Lianyungang, Lianyungang, Jiangsu, China | D30: DG;GC | E30: Piraeus / Shanghai, China | F30: USD | G30: 775 | H30: 1100 | I30: 1100 | J30: BAF; CAF; EMS; GAS; HQA; LSA; LSS; SEC; SUZ; THC | K30: =K29 -> INCL | L30: =$L$10 -> 60 | M30: =$M$10 -> EBS/ETS
B31: Algeciras | C31: Macao, Macau | D31: DG;GC | E31: Hong Kong, Hong Kong | F31: USD | G31: 850 | H31: 1175 | I31: 1175 | J31: BAF; CAF; EMS; GAS; HQA; LSA; LSS; SEC; SUZ; THC | K31: =K30 -> INCL | L31: =$L$10 -> 60 | M31: =$M$10 -> EBS/ETS
B32: Algeciras | C32: Manila, Metro Manila, Philippines | D32: DG;GC | E32: Port Klang / Hong Kong | F32: USD | G32: 925 | H32: 1275 | I32: 1275 | J32: BAF; CAF; EMS; GAS; HQA; LSA; LSS; SEC; SUZ; THC | K32: =K31 -> INCL | L32: =$L$10 -> 60 | M32: =$M$10 -> EBS/ETS
B33: Algeciras | C33: Nagoya, Aichi, Japan | D33: GC | E33: Piraeus / Hong Kong / WM1 | F33: USD | G33: 850 | H33: 1050 | I33: 1050 | J33: BAF; CAF; EMS; GAS; HQA; LSA; LSS; SEC; SUZ; THC | K33: =K32 -> INCL | L33: =$L$10 -> 60 | M33: =$M$10 -> EBS/ETS
... B63: Algeciras | C63: Zhuhai, Zhuhai, Guangdong, China | D63: DG;GC | E63: Piraeus / Hong Kong, Hong Kong;Shekou, Shenzhen, Guangdong, China | F63: USD | G63: 725 | H63: 950 | I63: 950 | J63: BAF; CAF; EMS; GAS; HQA; LSA; LSS; SEC; SUZ; THC | K63: =K62 -> INCL | L63: =$L$10 -> 60 | M63: =$M$10 -> EBS/ETS
B65: REMARKS
B66: a. Fletes validos para mercancia FAK (harmless). No incluye: MARMOL BLOQUE/PIELES/SCRAPS/HIGH VALUE CARGO
B67: b. Fletes incluyen CAF, BAF, GAS, SUZ, EMS, LSA y THC y estan sujetos DOC/AMS (for China & Japan)/T3 y resto de gastos locales
B68: c. Sujeto a los gastos de Destino
B69: d. Sujetos a VGM (VLC = EUR 10/cntr)
B70: e. B/L - M/F Correction on AMS : EUR 50 / correction
B71: f. B/L Fee EUR 100/BL for manual submission, EUR 30/BL for submission (BKG&SI) through My OOCL Center
B72: g. DG charge of USD 100/cntr, excluding PSA charges via T/S Singapore.
B73: h. DG charge of USD 150/20' Usd 200/40' To Port Klang as port of discharge.
B74: i. AMS CHINA/JAP: EUR 25/BL
B75: j. Sujetos a TCM EUR 10/cntr
B76: k. LSA (Low Sulphur Additional) DRY INCLUDED
... B79: n. SOC SURCHARGE: a consultar
B80: O. Emergency Bunker Surcharge: USD 60/20`& USD 120/40´ from 23/March/2026 | F80: Rule Tariff Detail
B82: Attention - for all DG cargo going to / via Singapore we will require MSDS sheet prior to shipment in order to determine acceptance / PSA costs!
B83: “PSA costs (DHT) tariff per 20’/40’/45’ for DG TSH via SIN w.e.f. 1 Nov 2023
B84: PSA 3/2F/2S: SGD 180/360/405
B85: PSA 2B/2C: SGD 930/1485/1643
B86: PSA 2A: SGD: 1080/1635/1793
B87: PSA 1S: SGD: 380/560/605
B88: PSA 1C/1N: SGD 1130/1685/1843
B89: PSA 2 (for Lighter UN1057): SGD 1690/2605/2853
B90: PSA 2 (except Lighter UN1057): SGD 1290/2205/2453
B91: PSA 1D: SGD 1490/2405/2653
B92: Pls check before booking acceptance. Subject DG acceptance and local regulations at destination
B93: CONSULTAR CON DPT COMERCIAL PARA CHEQUEAR TIPO DE PSA APLICABLE
... B97: http://www.oocl.com/eng/Pages/importantnoticeforratedocument.aspx

Sheet BCN-VLC to FAR EAST
E2: EXPORT BCN/VLC > FAR EAST | J2: SOLICITAR BOOKING A TRAVES DE FreightSmart - E-QUOTE (AB)
J3: RATE DATE: On board date
E4: ='BCN-VLC-ALG to W-E Africa'!F4 -> VALIDEZ: 1 Abril 2026 hasta 30 Abril 2026
D6: EMERGENCY BUNKER SURCHARGE: USD 60/20´DC & USD 120/40´DC or HC, from 23rd.March.26
B8: Origins* | C8: Destinations* | D8: Cargo Nature* | E8: via | F8: Currency* | G8: 20'GP - DRY | H8: 40'GP - DRY | I8: 40'HQ - DRY | J8: Included Charges | K8: LSA (TEU) | L8: EBS (TEU) | M8: Subject To | N8: payment Terms | O8: Remarks
B9: Barcelona/Valencia | C9: Bangkok, Thailand | D9: DG;GC | E9: Port Klang, Selangor, Malaysia;Singapore, Singapore | F9: USD | G9: 375 | H9: 475 | I9: 475 | J9: BAF; CAF; EMS; GAS; HQA; LSA; LSS; SEC; SUZ; THC | K9: INCL | L9: 60 | M9: EBS/ETS
B10: Barcelona/Valencia | C10: Belawan, Sumatera Utara, Indonesia | D10: DG;GC | E10: Port Klang, Selangor, Malaysia;Singapore, Singapore | F10: USD | G10: 450 | H10: 600 | I10: 600 | J10: BAF; CAF; EMS; GAS; HQA; LSA; LSS; SEC; SUZ; THC | K10: =K9 -> INCL | L10: =$L$10 -> 60 | M10: =$M$10 -> EBS/ETS
B11: Barcelona/Valencia | C11: Busan, South Korea | D11: GC | E11: Ningbo | F11: USD | G11: 195 | H11: 190 | I11: 190 | J11: BAF; CAF; EMS; GAS; HQA; LSA; LSS; SEC; SUZ; THC | K11: =K10 -> INCL | L11: =$L$10 -> 60 | M11: =$M$10 -> EBS/ETS | O11: WM1 TT 53 dias / WM2 T 78 dias
B12: Barcelona/Valencia | C12: Changsha, Changsha, Hunan, China | D12: DG;GC | E12: Shanghai, China | F12: USD | G12: 475 | H12: 675 | I12: 675 | J12: BAF; CAF; EMS; GAS; HQA; LSA; LSS; SEC; SUZ; THC | K12: =K11 -> INCL | L12: =$L$10 -> 60 | M12: =$M$10 -> EBS/ETS
B13: Barcelona/Valencia | C13: Chongqing, China | D13: DG;GC | E13: Shanghai, China | F13: USD | G13: 550 | H13: 850 | I13: 850 | J13: BAF; CAF; EMS; GAS; HQA; LSA; LSS; SEC; SUZ; THC | K13: =K12 -> INCL | L13: =$L$10 -> 60 | M13: =$M$10 -> EBS/ETS
B14: Barcelona/Valencia | C14: Da Nang, Vietnam | D14: DG;GC | E14: Singapore, Singapore | F14: USD | G14: 1025 | H14: 1675 | I14: 1675 | J14: BAF; CAF; EMS; GAS; HQA; LSA; LSS; SEC; SUZ; THC | K14: =K13 -> INCL | L14: =$L$10 -> 60 | M14: =$M$10 -> EBS/ETS
B15: Barcelona | C15: Dalian, Dalian, Liaoning, China | D15: GC | E15: Port Klang | F15: USD | G15: 150 | H15: 125 | I15: 125 | J15: BAF; CAF; EMS; GAS; HQA; LSA; LSS; SEC; SUZ; THC | K15: =K14 -> INCL | L15: =$L$10 -> 60 | M15: =$M$10 -> EBS/ETS
B16: Valencia | C16: Dalian, Dalian, Liaoning, China | D16: GC | E16: Singapore WM1 | F16: USD | G16: 150 | H16: 125 | I16: 125 | J16: BAF; CAF; EMS; GAS; HQA; LSA; LSS; SEC; SUZ; THC | K16: =K15 -> INCL | L16: =$L$10 -> 60 | M16: =$M$10 -> EBS/ETS
B17: Valencia | C17: Davao City, Davao del Sur, Philippines | D17: DG;GC | E17: Singapore | F17: USD | G17: 1100 | H17: 1875 | I17: 1875 | J17: BAF; CAF; EMS; GAS; HQA; LSA; LSS; SEC; SUZ; THC | K17: =K16 -> INCL | L17: =$L$10 -> 60 | M17: =$M$10 -> EBS/ETS
B18: Barcelona/Valencia | C18: Fuqing, Fuzhou, Fujian, China | D18: DG;GC | E18: Ningbo, Ningbo, Zhejiang, China | F18: USD | G18: 375 | H18: 525 | I18: 525 | J18: BAF; CAF; EMS; GAS; HQA; LSA; LSS; SEC; SUZ; THC | K18: =K17 -> INCL | L18: =$L$10 -> 60 | M18: =$M$10 -> EBS/ETS
B19: Barcelona/Valencia | C19: Fuzhou, Fuzhou, Fujian, China | D19: DG;GC | E19: Xiamen | F19: USD | G19: 350 | H19: 475 | I19: 475 | J19: BAF; CAF; EMS; GAS; HQA; LSA; LSS; SEC; SUZ; THC | K19: =K18 -> INCL | L19: =$L$10 -> 60 | M19: =$M$10 -> EBS/ETS
B20: Barcelona/Valencia | C20: Guangzhou, Guangzhou, Guangdong, China | D20: DG;GC | E20: Hong kong | F20: USD | G20: 300 | H20: 425 | I20: 425 | J20: BAF; CAF; EMS; GAS; HQA; LSA; LSS; SEC; SUZ; THC | K20: =K19 -> INCL | L20: =$L$10 -> 60 | M20: =$M$10 -> EBS/ETS
B21: Barcelona | C21: Hai Phong, Vietnam | D21: DG;GC | E21: Port Klang | F21: USD | G21: 300 | H21: 400 | I21: 400 | J21: BAF; CAF; EMS; GAS; HQA; LSA; LSS; SEC; SUZ; THC | K21: =K20 -> INCL | L21: =$L$10 -> 60 | M21: =$M$10 -> EBS/ETS
B22: Valencia | C22: Hai Phong, Vietnam | D22: DG;GC | E22: Singapore | F22: USD | G22: 350 | H22: 425 | I22: 425 | J22: BAF; CAF; EMS; GAS; HQA; LSA; LSS; SEC; SUZ; THC | K22: =K21 -> INCL | L22: =$L$10 -> 60 | M22: =$M$10 -> EBS/ETS
B23: Barcelona/Valencia | C23: Hakata, Fukuoka, Japan | D23: DG;GC | E23: Kobe, Hyogo-ken, Japan | F23: USD | G23: =G33+250 -> 650 | H23: =H33+350 -> 800 | I23: =H23 -> 800 | J23: BAF; CAF; EMS; GAS; HQA; LSA; LSS; SEC; SUZ; THC | K23: =K22 -> INCL | L23: =$L$10 -> 60 | M23: =$M$10 -> EBS/ETS
B24: Barcelona/Valencia | C24: Ho Chi Minh, Vietnam | D24: DG;GC | E24: Singapore | F24: USD | G24: 300 | H24: 400 | I24: 400 | J24: BAF; CAF; EMS; GAS; HQA; LSA; LSS; SEC; SUZ; THC | K24: =K23 -> INCL | L24: =$L$10 -> 60 | M24: =$M$10 -> EBS/ETS
B25: Barcelona | C25: Hong Kong, Hong Kong | D25: GC | E25: via Pklang | F25: USD | G25: 225 | H25: 200 | I25: 200 | J25: BAF; CAF; EMS; GAS; HQA; LSA; LSS; SEC; SUZ; THC | K25: =K24 -> INCL | L25: =$L$10 -> 60 | M25: =$M$10 -> EBS/ETS
B26: Valencia | C26: Hong Kong, Hong Kong | D26: GC | E26: Direct WM1 | F26: USD | G26: 150 | H26: 125 | I26: 125 | J26: BAF; CAF; EMS; GAS; HQA; LSA; LSS; SEC; SUZ; THC | K26: =K25 -> INCL | L26: =$L$10 -> 60 | M26: =$M$10 -> EBS/ETS
B27: Barcelona/Valencia | C27: Huangpu, Guangzhou, Guangdong, China | D27: DG;GC | E27: Nansha / HKG | F27: USD | G27: 350 | H27: 400 | I27: 400 | J27: BAF; CAF; EMS; GAS; HQA; LSA; LSS; SEC; SUZ; THC | K27: =K26 -> INCL | L27: =$L$10 -> 60 | M27: =$M$10 -> EBS/ETS
B28: Valencia | C28: Jakarta, Indonesia | D28: DG;GC | E28: Port Klang | F28: USD | G28: 425 | H28: 525 | I28: 525 | J28: BAF; CAF; EMS; GAS; HQA; LSA; LSS; SEC; SUZ; THC | K28: =K27 -> INCL | L28: =$L$10 -> 60 | M28: =$M$10 -> EBS/ETS
B29: Barcelona | C29: Jakarta, Indonesia | D29: DG;GC | E29: Port Klang | F29: USD | G29: 425 | H29: 525 | I29: 525 | J29: BAF; CAF; EMS; GAS; HQA; LSA; LSS; SEC; SUZ; THC | K29: =K28 -> INCL | L29: =$L$10 -> 60 | M29: =$M$10 -> EBS/ETS
B30: Barcelona | C30: Kaohsiung, Taiwan | D30: GC | E30: Directo | F30: USD | G30: 150 | H30: 125 | I30: 125 | J30: BAF; CAF; EMS; GAS; HQA; LSA; LSS; SEC; SUZ; THC | K30: =K29 -> INCL | L30: =$L$10 -> 60 | M30: =$M$10 -> EBS/ETS
B31: Valencia | C31: Kaohsiung, Taiwan | D31: GC | E31: Directo | F31: USD | G31: 150 | H31: 125 | I31: 125 | J31: BAF; CAF; EMS; GAS; HQA; LSA; LSS; SEC; SUZ; THC | K31: =K30 -> INCL | L31: =$L$10 -> 60 | M31: =$M$10 -> EBS/ETS
B32: Barcelona/Valencia | C32: Keelung, Taiwan | D32: DG;GC | E32: Kaohsiung, Taiwan | F32: USD | G32: 500 | H32: 475 | I32: 475 | J32: BAF; CAF; EMS; GAS; HQA; LSA; LSS; SEC; SUZ; THC | K32: =K31 -> INCL | L32: =$L$10 -> 60 | M32: =$M$10 -> EBS/ETS
B33: Valencia | C33: Kobe, Hyogo-ken, Japan | D33: GC | E33: Hong Kong / WM1 | F33: USD | G33: 400 | H33: 450 | I33: 450 | J33: BAF; CAF; EMS; GAS; HQA; LSA; LSS; SEC; SUZ; THC | K33: =K32 -> INCL | L33: =$L$10 -> 60 | M33: =$M$10 -> EBS/ETS
B34: Barcelona | C34: Kobe, Hyogo-ken, Japan | D34: GC | E34: Xiamen / WM2 | F34: USD | G34: 400 | H34: 450 | I34: 450 | J34: BAF; CAF; EMS; GAS; HQA; LSA; LSS; SEC; SUZ; THC | K34: =K33 -> INCL | L34: =$L$10 -> 60 | M34: =$M$10 -> EBS/ETS
B35: Barcelona/Valencia | C35: Laem Chabang, Chon Buri, Thailand | D35: DG;GC | E35: Port Klang, Selangor, Malaysia;Singapore, Singapore | F35: USD | G35: 350 | H35: 450 | I35: 450 | J35: BAF; CAF; EMS; GAS; HQA; LSA; LSS; SEC; SUZ; THC | K35: =K34 -> INCL | L35: =$L$10 -> 60 | M35: =$M$10 -> EBS/ETS
... B76: Barcelona/Valencia | C76: Zhuhai, Zhuhai, Guangdong, China | D76: DG;GC | E76: Hong Kong, Hong Kong;Shekou, Shenzhen, Guangdong, China | F76: USD | G76: 375 | H76: 475 | I76: 475 | J76: BAF; CAF; EMS; GAS; HQA; LSA; LSS; SEC; SUZ; THC | K76: =K75 -> INCL | L76: =$L$10 -> 60 | M76: =$M$10 -> EBS/ETS
B78: REMARKS
B79: a. Fletes validos para mercancia FAK (harmless). No incluye: MARMOL BLOQUE/PIELES/SCRAPS/HIGH VALUE CARGO
B80: b. Fletes incluyen CAF, BAF, GAS & SUZ y estan sujetos DOC/AMS (for China & Japan)/T3
B81: c. Sujeto a los gastos de Destino
B82: d. Sujetos a VGM (VLC = EUR 10/cntr)
B83: e. B/L - M/F Correction on AMS : EUR 50 / correction
B84: f. B/L Fee EUR 100/BL for manual submission, EUR 30/BL for submission (BKG&SI) through My OOCL Center
B85: g. DG charge of USD 100/cntr, excluding PSA charges via T/S Singapore.
B86: h. DG charge of USD 150/20' Usd 200/40' To Port Klang as port of discharge.
B87: i. AMS CHINA/JAP: EUR 25/BL
B88: j. Sujetos a TCM Eur 10/cntr
B89: k. LSA (Low Sulphur Additional) DRY INCLUDED
... B92: n. SOC SURCHARGE: a consultar
B93: O. Emergency Bunker Surcharge: USD 60/20`& USD 120/40´ from 23/March/2026 | F93: Rule Tariff Detail
B95: Attention - for all DG cargo going to / via Singapore we will require MSDS sheet prior to shipment in order to determine acceptance / PSA costs!
B96: “PSA costs (DHT) tariff per 20’/40’/45’ for DG TSH via SIN w.e.f. 1 Nov 2023
B97: PSA 3/2F/2S: SGD 180/360/405
B98: PSA 2B/2C: SGD 930/1485/1643
B99: PSA 2A: SGD: 1080/1635/1793
B100: PSA 1S: SGD: 380/560/605
B101: PSA 1C/1N: SGD 1130/1685/1843
B102: PSA 2 (for Lighter UN1057): SGD 1690/2605/2853
B103: PSA 2 (except Lighter UN1057): SGD 1290/2205/2453
B104: PSA 1D: SGD 1490/2405/2653
B105: Pls check before booking acceptance. Subject DG acceptance and local regulations at destination
B106: CONSULTAR CON DPT COMERCIAL PARA CHEQUEAR TIPO DE PSA APLICABLE
... B110: http://www.oocl.com/eng/Pages/importantnoticeforratedocument.aspx

Sheet USA
D2: . | E2: EXPORT BCN/VLC/ALG > USA | J2: Contrato 85349
J3: RATE DATE: Fecha de entrada en terminal/GATE IN
D4: . | E4: ='BCN-VLC-ALG to W-E Africa'!F4 -> VALIDEZ: 1 Abril 2026 hasta 30 Abril 2026 | J4: Rates NOT applicable for Dangerous Cargo (class 1&7). Exclude high value cargo (>$500,000 value).
C6: EMERGENCY BUNKER SURCHARGE: USD 150/20´DC & USD 300/40´DC or HC, from 13th.April.26
B8: Origins* | C8: Destinations* | D8: Cargo Nature* | E8: T/time (BCN/VLC) | F8: via | G8: Currency* | H8: 20'GP - DRY | I8: 40'GP - DRY | J8: 40'HQ - DRY | K8: Included Charges | L8: FCR (TEU) | M8: EBS (TEU) | N8: Subject To | O8: payment Terms | P8: Remarks
B9: BARCELONA | C9: New York, New York, New York, United States | D9: GC | E9: 15 dias | F9: Valencia | G9: USD | H9: 1630 | I9: 1730 | J9: =I9 -> 1730 | K9: CAF; CSC; FCR; SED | L9: INCLUDED | M9: 150 | N9: EBS;THD;ETS
B10: BARCELONA | C10: Miami, Miami-Dade, Florida, United States | D10: GC | E10: 21 dias | F10: Valencia | G10: USD | H10: 1630 | I10: 1730 | J10: =I10 -> 1730 | K10: CAF; CSC; FCR; SED | L10: INCLUDED | M10: =$M$9 -> 150 | N10: =$N$9 -> EBS;THD;ETS
B11: BARCELONA | C11: Norfolk, Norfolk, Virginia, United States | D11: GC | E11: 17 dias | F11: Valencia | G11: USD | H11: 1630 | I11: 1730 | J11: =I11 -> 1730 | K11: CAF; CSC; FCR; SED | L11: INCLUDED | M11: =$M$9 -> 150 | N11: =$N$9 -> EBS;THD;ETS
B12: BARCELONA | C12: Savannah, Chatham, Georgia, United States | D12: GC | E12: 19 dias | F12: Valencia | G12: USD | H12: 1630 | I12: 1730 | J12: =I12 -> 1730 | K12: CAF; CSC; FCR; SED | L12: INCLUDED | M12: =$M$9 -> 150 | N12: =$N$9 -> EBS;THD;ETS
B13: VALENCIA | C13: New York, New York, New York, United States | D13: GC | E13: 12 dias | F13: Directo | G13: USD | H13: 1480 | I13: 1580 | J13: 1580 | K13: CAF; CSC; FCR; SED | L13: INCLUDED | M13: =$M$9 -> 150 | N13: =$N$9 -> EBS;THD;ETS
B14: VALENCIA | C14: Miami, Miami-Dade, Florida, United States | D14: GC | E14: 21 dias | F14: Directo | G14: USD | H14: 1480 | I14: 1580 | J14: 1580 | K14: CAF; CSC; FCR; SED | L14: INCLUDED | M14: =$M$9 -> 150 | N14: =$N$9 -> EBS;THD;ETS
B15: VALENCIA | C15: Norfolk, Norfolk, Virginia, United States | D15: GC | E15: 14 dias | F15: Directo | G15: USD | H15: 1480 | I15: 1580 | J15: 1580 | K15: CAF; CSC; FCR; SED | L15: INCLUDED | M15: =$M$9 -> 150 | N15: =$N$9 -> EBS;THD;ETS
B16: VALENCIA | C16: Savannah, Chatham, Georgia, United States | D16: GC | E16: 16 dias | F16: Directo | G16: USD | H16: 1480 | I16: 1580 | J16: 1580 | K16: CAF; CSC; FCR; SED | L16: INCLUDED | M16: =$M$9 -> 150 | N16: =$N$9 -> EBS;THD;ETS
B17: ALGECIRAS | C17: New York, New York, New York, United States | D17: GC | E17: 9 dias | F17: Directo | G17: USD | H17: 1480 | I17: 1580 | J17: 1580 | K17: CAF; CSC; FCR; SED | L17: INCLUDED | M17: =$M$9 -> 150 | N17: =$N$9 -> EBS;THD;ETS
B18: ALGECIRAS | C18: Miami, Miami-Dade, Florida, United States | D18: GC | E18: 11 dias | F18: Directo | G18: USD | H18: 1480 | I18: 1580 | J18: 1580 | K18: CAF; CSC; FCR; SED | L18: INCLUDED | M18: =$M$9 -> 150 | N18: =$N$9 -> EBS;THD;ETS
B19: ALGECIRAS | C19: Norfolk, Norfolk, Virginia, United States | D19: GC | E19: 13 dias | F19: Directo | G19: USD | H19: 1480 | I19: 1580 | J19: 1580 | K19: CAF; CSC; FCR; SED | L19: INCLUDED | M19: =$M$9 -> 150 | N19: =$N$9 -> EBS;THD;ETS
B20: ALGECIRAS | C20: Savannah, Chatham, Georgia, United States | D20: GC | E20: 19 dias | F20: Directo | G20: USD | H20: 1480 | I20: 1580 | J20: 1580 | K20: CAF; CSC; FCR; SED | L20: INCLUDED | M20: =$M$9 -> 150 | N20: =$N$9 -> EBS;THD;ETS
B21: (*) Please note that the rail CY in Houston is located away from the port and therefore the maximum payload can only be per the standard road weight limits (there are no tri-axle services available)
B23: RAIL RAMPS // NO se acepta carga IMO //
B24: Location | C24: Postal Code | D24: Mode | E24: Over Location | F24: Transport Mode | G24: Rate 20 | H24: Rate 40 | I24: Rate 40H | J24: Currency | K24: Cargo Nature
B25: Atlanta, Fulton, Georgia, United States | C25: ="30301" -> 30301 | D25: CY | E25: Savannah, Chatham, Georgia, United States | F25: Rail | G25: 400 | H25: 500 | I25: 500 | J25: USD | K25: GC
B26: Baltimore, Baltimore, Maryland, United States** | C26: ="21225" -> 21225 | D26: CY | E26: Norfolk, Norfolk, Virginia, United States | F26: Barge | G26: 1000 | H26: 1000 | I26: 1000 | J26: USD | K26: GC | L26: **
B27: Charlotte, Mecklenburg, North Carolina, United States | C27: ="28208" -> 28208 | D27: CY | E27: Savannah, Chatham, Georgia, United States | F27: Rail | G27: 425 | H27: 575 | I27: 575 | J27: USD | K27: GC
B28: Chicago, Cook, Illinois, United States | C28: ="60630" -> 60630 | D28: CY | E28: Norfolk, Norfolk, Virginia, United States | F28: Rail | G28: 550 | H28: 725 | I28: 725 | J28: USD | K28: GC
B29: Cincinnati, Hamilton, Ohio, United States | C29: ="45232" -> 45232 | D29: CY | E29: Norfolk, Norfolk, Virginia, United States | F29: Rail | G29: 750 | H29: 970 | I29: 970 | J29: USD | K29: GC
B30: Cleveland, Cuyahoga, Ohio, United States | C30: ="44110" -> 44110 | D30: CY | E30: Norfolk, Norfolk, Virginia, United States | F30: Rail | G30: 725 | H30: 850 | I30: 850 | J30: USD | K30: GC
B31: Columbus, Franklin, Ohio, United States | C31: ="43216" -> 43216 | D31: CY | E31: Norfolk, Norfolk, Virginia, United States | F31: Rail | G31: 725 | H31: 850 | I31: 850 | J31: USD | K31: GC
B32: Detroit, Wayne, Michigan, United States | C32: ="48229" -> 48229 | D32: CY | E32: Norfolk, Norfolk, Virginia, United States | F32: Rail | G32: 750 | H32: 900 | I32: 900 | J32: USD | K32: GC
B33: Front Royal, Fauquier, Virginia, United States | C33: ="22630" -> 22630 | D33: CY | E33: Norfolk, Norfolk, Virginia, United States | F33: Rail | G33: 700 | H33: 700 | I33: 700 | J33: USD | K33: GC
B34: Huntsville, Madison, Alabama, United States | C34: ="35810" -> 35810 | D34: CY | E34: Savannah, Chatham, Georgia, United States | F34: Rail | G34: 800 | H34: 900 | I34: 900 | J34: USD | K34: GC
B35: Kansas City, Jackson, Missouri, United States | C35: ="64149" -> 64149 | D35: CY | E35: Norfolk, Norfolk, Virginia, United States | F35: Rail | G35: 1025 | H35: 1075 | I35: 1075 | J35: USD | K35: GC
B36: Louisville, Jefferson, Kentucky, United States | C36: ="40206" -> 40206 | D36: CY | E36: Norfolk, Norfolk, Virginia, United States | F36: Rail | G36: 700 | H36: 1000 | I36: 1000 | J36: USD | K36: GC
B37: Memphis, Shelby, Tennessee, United States | C37: ="38109" -> 38109 | D37: CY | E37: Savannah, Chatham, Georgia, United States | F37: Rail | G37: 725 | H37: 950 | I37: 950 | J37: USD | K37: GC
B38: Minneapolis, Hennepin, Minnesota, United States** | C38: ="55447" -> 55447 | D38: CY | E38: Norfolk, Norfolk, Virginia, United States | F38: Rail | G38: 1775 | H38: 2000 | I38: 2000 | J38: USD | K38: GC | L38: **
B39: Nashville, Davidson, Tennessee, United States | C39: ="37201" -> 37201 | D39: CY | E39: Savannah, Chatham, Georgia, United States | F39: Rail | G39: 800 | H39: 1000 | I39: 1000 | J39: USD | K39: GC
B40: Pittsburgh, Allegheny, Pennsylvania, United States | C40: ="15206" -> 15206 | D40: CY | E40: New York, New York, New York, United States | F40: Rail | G40: 750 | H40: 800 | I40: 800 | J40: USD | K40: GC
B41: Saint Louis, Saint Louis, Missouri, United States | C41: ="63144" -> 63144 | D41: CY | E41: Norfolk, Norfolk, Virginia, United States | F41: Rail | G41: 825 | H41: 1000 | I41: 1000 | J41: USD | K41: GC
B42: Worcester, Worcester, Massachusetts, United States(Boston) | C42: 01604 | D42: CY | E42: New York, New York, New York, United States | F42: Rail | G42: 1050 | H42: 1100 | I42: 1100 | J42: USD | K42: GC
B45: (**) Aplica el peso maximo de carretera ** Standard Road weight limits apply of 17.92T and 20.19T tare weight
B48: THD (CARGA DRY): | C48: USD 500/20' Usd 600/40' - NO incluido en el flete *** La THD por defecto se aplica COLLECT. En caso de que deba aplicarse prepaid debe indicarse tanto al solicitar el booking como al enviar las SI *** | H48: * EXCEPCION para EFECTOS PERSONALES: FLETE/FUEL/THD seran SIEMPRE PREPAID *
B49: THC Origen (CSC) - INCLUDED | C49: EUR 210/cntr
B50: Miami Wharfage | C50: USD 38,75/teu
B51: Houston Wharfage | C51: USD 63,06/cntr | D51: No se aceptan IMO's 1.4S 1.4G and 7.
B52: IMO Surcharge (except Savannah) | C52: USD 250/cntr | D52: No se aceptan IMO's 1.4S 1.4G and 7.
B53: IMO Surcharge to Savannah) | C53: USD 325/cntr
B54: IMO Documentation | C54: EUR 40/UN
B55: SMD (Security Manifest Doc fee): | C55: EUR 25/BL&transmission
B56: TCM (Terminal Customs Monitoring) | C56: EUR 10/cntr
B57: Documentación: | C57: EUR 100/BL
B58: Tasa mercancía + Tara cntr. BCN: | C58: EUR 21.20/20' EUR 31,80/40'
B59: Tasa mercancía + Tara cntr. VLC: | C59: EUR 25.44/20' EUR 38.16/40'
B60: Tasa mercancía + Tara cntr. ALR: | C60: EUR 26.55/20' EUR 35.78/40'
B61: Quebranto bancario: | C61: 1% s/ gastos en moneda extranjera
B62: VGM Valencia: | C62: EUR 10/cntr
B63: VGM Barcelona: | C63: For shippers account / If done by OOCL EUR 18/cntr
B64: VGM Algeciras: | C64: For shippers account /Only if ONC is done by OOCL then VGM If done by OOCL EUR 55/cntr
... B67: EU ETS Compliance Fee: | C67: EUR 69/20' & EUR 138/40'
B68: EBS Emergency Bunker Surcharge | C68: USD 150/20' & USD 300/40' only from 13th.April.2026 gate in | F68: Rule Tariff Detail
B70: PESO MAXIMO AUTORIZADO PARA CIRCULAR POR FERROCARRIL EL INTERIOR DE EEUU
B71: 20´dv- 19.950 kgs
B72: 40´dv-hq- 23.580 kgs
B73: ** Si hay un traslado de terminal en los transportes Rail, el peso máximo permitido es el mismo que si se moviera por carretera (se reduce)** / Rail/Ramp via Charleston peso maximo el de carretera solo
B74: Se puede aceptar hasta 20' gp 21.540 kgs y 40'gp-hq 26.300 kgs con un adicional de OverWeight de USD 230/cntr
B76: PESO MAXIMO AUTORIZADO PARA CIRCULAR POR CARRETERA EL INTERIOR DE EEUU
B77: · 20´dv- 39,500lbs – 17920 kgs
B78: · 40´dv- 44,500lbs – 20190 kgs
B80: Pesos máximos que podremos aceptar para sus embarques hasta puerto americano:
B82: USA DRY | C82: 20 ft GP | D82: 40 ft GP/HQ | E82: 45 ft HQ | F82: Service | G82: Action required
B83: Maximum cargo weight allowed for use of OOCL container | C83: 62.100 lbs- 28165KGS | D83: 58,700 lbs-26623KGS | E83: 56,600 lbs- 25671KGS | F83: Port CY service only | G83: Cargo weight can not move via highway. Transload arrangements, highway permits and special use equipment are the responsibility of the customer. Customer is responsible for all additional cost, including transload, highway weight penalty/fine, etc. OOCL does not provide chassis. Requires re-work at marine terminal before highway move.
B86: INLAND RAMP STORAGE COST:
B87: Customer is responsible for rail ramp storage charges, according to tariff terms. Allow 48 hours for special chassis or permit request.
B88: If special equipment not available, OOCL is not responsible for delay, customer is responsible for storage cost.
B90: FREE TIME EN USA:
B91: Rule Tariff Detail (oocl.com)

Sheet BCN-VLC-ALG to INDIA-PAKISTAN
E2: EXPORT BCN/VLC/ALG > INDIA/PAKISTAN | J2: SOLICITAR BOOKING A TRAVES DE FreightSmart - E-QUOTE (AB)
J3: RATE DATE: On board date
E4: ='BCN-VLC-ALG to W-E Africa'!F4 -> VALIDEZ: 1 Abril 2026 hasta 30 Abril 2026
C6: EMERGENCY BUNKER SURCHARGE: USD 60/20´DC & USD 120/40´DC or HC, from 23rd.March.26
B8: Origins* | C8: Destinations* | D8: Cargo Nature* | E8: via | F8: Currency* | G8: 20'GP - DRY | H8: 40'GP - DRY | I8: 40'HQ - DRY | J8: Included Charges | K8: LSA (TEU) | L8: EBS (TEU) | M8: Subject To | N8: payment Terms | O8: Remarks
B9: Barcelona | C9: Chattogram, Bangladesh | D9: DG;GC | E9: Via Fos sur Mer/Port Klang / 57 dias | F9: USD | G9: 1300 | H9: 1600 | I9: 1600 | J9: CAF, BAF, GAS, SUZ, LSA, EMS, THC | K9: INCL | L9: 60 | M9: EBS/DOC/T3/ETS | N9: Prepaid
B10: Valencia | C10: Chattogram, Bangladesh | D10: DG;GC | E10: Via Singapore / 43 dias | F10: USD | G10: 1300 | H10: 1600 | I10: 1600 | J10: CAF, BAF, GAS, SUZ, LSA, EMS, THC | K10: INCL | L10: =$L$9 -> 60 | M10: =M9 -> EBS/DOC/T3/ETS | N10: Prepaid
B11: Barcelona/Valencia | C11: Kattupalli, India | D11: DG;GC | E11: Via Jeddah / 37 dias | F11: USD | G11: SERVICIO SUSPENDIDO | J11: CAF, BAF, GAS, SUZ, LSA, EMS, THC | K11: INCL | L11: =$L$9 -> 60 | M11: =M10 -> EBS/DOC/T3/ETS | N11: Prepaid
B12: Barcelona/Valencia | C12: Colombo, Sri Lanka | D12: DG;GC | E12: Via Jeddah / 28 dias | F12: USD | G12: SERVICIO SUSPENDIDO | J12: CAF, BAF, GAS, SUZ, LSA, EMS, THC | K12: INCL | L12: =$L$9 -> 60 | M12: =M11 -> EBS/DOC/T3/ETS | N12: Prepaid
B13: Barcelona | C13: Haldia, West Bengal, India | D13: DG;GC | E13: Port Kelang / 45 dias | F13: USD | G13: 1550 | H13: 1850 | I13: 1850 | J13: CAF, BAF, GAS, SUZ, LSA, EMS, THC | K13: INCL | L13: =$L$9 -> 60 | M13: =M12 -> EBS/DOC/T3/ETS | N13: Prepaid
B14: Valencia | C14: Haldia, West Bengal, India | D14: DG;GC | E14: via Port Kelang / 50 dias | F14: USD | G14: 1550 | H14: 1850 | I14: 1850 | J14: CAF, BAF, GAS, SUZ, LSA, EMS, THC | K14: INCL | L14: =$L$9 -> 60 | M14: =M13 -> EBS/DOC/T3/ETS | N14: Prepaid
B15: Algeciras | C15: Keamari, Karachi, Sindh, Pakistan | D15: DG;GC | E15: Jebel Ali WM3 31 days | F15: USD | G15: SERVICIO SUSPENDIDO | J15: CAF, BAF, GAS, SUZ, LSA, EMS, THC | K15: INCL | L15: =$L$9 -> 60 | M15: EBS/RSM/DOC/T3/ETS | N15: Prepaid | O15: Subject to RSM: USD 200/CNTR
B16: Barcelona | C16: Keamari, Karachi, Sindh, Pakistan | D16: DG;GC | E16: Piraeus 31 dias | F16: USD | G16: SERVICIO SUSPENDIDO | J16: CAF, BAF, GAS, SUZ, LSA, EMS, THC | K16: INCL | L16: =$L$9 -> 60 | M16: =M15 -> EBS/RSM/DOC/T3/ETS | N16: Prepaid | O16: Subject to RSM: USD 200/CNTR
B17: Valencia | C17: Keamari, Karachi, Sindh, Pakistan | D17: DG;GC | E17: Piraeus/Jebel Ali WM3 31 days | F17: USD | G17: SERVICIO SUSPENDIDO | J17: CAF, BAF, GAS, SUZ, LSA, EMS, THC | K17: INCL | L17: =$L$9 -> 60 | M17: =M15 -> EBS/RSM/DOC/T3/ETS | N17: Prepaid | O17: Subject to RSM: USD 200/CNTR
B18: Barcelona | C18: Kolkata, West Bengal, India | D18: DG;GC | E18: via Port Kelang / 48 dias | F18: USD | G18: 1550 | H18: 1850 | I18: 1850 | J18: CAF, BAF, GAS, SUZ, LSA, EMS, THC | K18: INCL | L18: =$L$9 -> 60 | M18: =$M$14 -> EBS/DOC/T3/ETS | N18: Prepaid
B19: Valencia | C19: Kolkata, West Bengal, India | D19: DG;GC | E19: via Port Kelang / 50 dias | F19: USD | G19: 1550 | H19: 1850 | I19: 1850 | J19: CAF, BAF, GAS, SUZ, LSA, EMS, THC | K19: INCL | L19: =$L$9 -> 60 | M19: =$M$14 -> EBS/DOC/T3/ETS | N19: Prepaid
B20: Algeciras | C20: Mundra, Gujarat, India | D20: DG;GC | E20: Direct / IP1 / 39 dias | F20: USD | G20: 750 | H20: 900 | I20: 900 | J20: CAF, BAF, GAS, SUZ, LSA, EMS, THC | K20: INCL | L20: =$L$9 -> 60 | M20: =$M$14 -> EBS/DOC/T3/ETS | N20: Prepaid
B21: Barcelona | C21: Mundra, Gujarat, India | D21: DG;GC | E21: Directo WM3/ 32 dias | F21: USD | G21: SERVICIO SUSPENDIDO | J21: CAF, BAF, GAS, SUZ, LSA, EMS, THC | K21: INCL | L21: =$L$9 -> 60 | M21: =$M$14 -> EBS/DOC/T3/ETS | N21: Prepaid
B22: Valencia | C22: Mundra, Gujarat, India | D22: DG;GC | E22: Piraeus WM3/ 35 dias | F22: USD | G22: SERVICIO SUSPENDIDO | J22: CAF, BAF, GAS, SUZ, LSA, EMS, THC | K22: INCL | L22: =$L$9 -> 60 | M22: =$M$14 -> EBS/DOC/T3/ETS | N22: Prepaid
B23: Algeciras | C23: Nhava Sheva, Maharashtra, India | D23: DG;GC | E23: Direct / IP1 / 35 dias | F23: USD | G23: 750 | H23: 900 | I23: 900 | J23: CAF, BAF, GAS, SUZ, LSA, EMS, THC | K23: INCL | L23: =$L$9 -> 60 | M23: =$M$14 -> EBS/DOC/T3/ETS | N23: Prepaid
B24: Barcelona | C24: Nhava Sheva, Maharashtra, India | D24: DG;GC | E24: Piraeus WM3/ 35 dias | F24: USD | G24: SERVICIO SUSPENDIDO | J24: CAF, BAF, GAS, SUZ, LSA, EMS, THC | K24: INCL | L24: =$L$9 -> 60 | M24: =$M$14 -> EBS/DOC/T3/ETS | N24: Prepaid
B25: Valencia | C25: Nhava Sheva, Maharashtra, India | D25: DG;GC | E25: Piraeus WM3/ 37 dias | F25: USD | G25: SERVICIO SUSPENDIDO | J25: CAF, BAF, GAS, SUZ, LSA, EMS, THC | K25: INCL | L25: =$L$9 -> 60 | M25: =$M$14 -> EBS/DOC/T3/ETS | N25: Prepaid
B26: Barcelona/Valencia | C26: Visakhapatnam, Andhra Pradesh, India | D26: DG;GC | E26: via Jeddah / 33 dias | F26: USD | G26: SERVICIO SUSPENDIDO | J26: CAF, BAF, GAS, SUZ, LSA, EMS, THC | K26: INCL | L26: =$L$9 -> 60 | M26: =$M$14 -> EBS/DOC/T3/ETS | N26: Prepaid
B28: REMARKS
B29: a. Fletes validos para mercancia FAK (harmless). No incluye: MARMOL BLOQUE/PIELES/SCRAPS/HIGH VALUE CARGO
B30: b. Fletes incluyen CAF, BAF, GAS, EMS, LSA, THC origen & SUZ y estan sujetos DOC/AMS/T3 y resto de gastos locales | L30: .
B31: c. Sujeto a los gastos de Destino
B32: d. Sujetos a VGM (VLC = EUR/10 cntr)
B33: e. B/L - M/F Correction on AMS : EUR 50 / correction
B34: f. B/L Fee EUR 100/BL for manual submission, EUR 30/BL for submission (BKG&SI) through My OOCL Center
B35: g. DG charge of USD 100/cntr, excluding PSA charges via T/S Singapore .
B36: h. DG charge of USD 150/20' Usd 200/40' To Port Klang as port of discharge.
B37: i. DG charge of USD 75/20' Usd 75/40' To India and Pakistan services not routed via Port Klang or Singapore.
B38: j. Sujetos a TCM EUR/10 cntr)
B39: k. LSA (Low Sulphur Additional) DRY INCLUIDO
B40: l. EU ETS compliance Fee - Usd 34/x20' & USD 68/40' - PREPAID
B41: m. SOC SURCHARGE: a consultar
B42: n. EMS (Emergency surcharge) INCLUDED (USD 100/TEU)
... B44: p. DG Documentation fee: Eur 40,- x ONU (maximo 3 x doc)
B45: q. Emergency Bunker Surcharge: USD 60/20`& USD 120/40´ from 23/March/2026 | F45: Rule Tariff Detail
B47: Attention - for all DG cargo going to / via Singapore we will require MSDS sheet prior to shipment in order to determine acceptance / PSA costs!
B48: “PSA costs (DHT) tariff per 20’/40’/45’ for DG TSH via SIN w.e.f. 1 Nov 2023
B49: PSA 3/2F/2S: SGD 180/360/405
B50: PSA 2B/2C: SGD 930/1485/1643
B51: PSA 2A: SGD: 1080/1635/1793
B52: PSA 1S: SGD: 380/560/605
B53: PSA 1C/1N: SGD 1130/1685/1843
B54: PSA 2 (for Lighter UN1057): SGD 1690/2605/2853
B55: PSA 2 (except Lighter UN1057): SGD 1290/2205/2453
B56: PSA 1D: SGD 1490/2405/2653
B57: Pls check before booking acceptance. Subject DG acceptance and local regulations at destination
B58: CONSULTAR CON DPT COMERCIAL PARA CHEQUEAR TIPO DE PSA APLICABLE
... B61: http://www.oocl.com/eng/Pages/importantnoticeforratedocument.aspx

Sheet SUDAMERICA
E2: EXPORT ALG/BCN/VLC > SUDAMERICA | K2: SOLICITAR BOOKING A TRAVES DE FreightSmart - E-QUOTE (AB)
K3: RATE DATE: On board date
E4: ='BCN-VLC-ALG to W-E Africa'!F4 -> VALIDEZ: 1 Abril 2026 hasta 30 Abril 2026 | K4: 14 free days dem/det(2in1) at POD
D6: EMERGENCY BUNKER SURCHARGE: EUR 75/20´DC & EUR 150/40´DC or HC, from 23rd.March.26
B8: Origins* | C8: Destinations* | D8: Cargo Nature* | E8: T/time (BCN/VLC) | F8: via | G8: Currency* | H8: 20'GP - DRY | I8: 40'GP - DRY | J8: 40'HQ - DRY | K8: Included Charges | L8: FCR (TEU) | M8: EBS (TEU) | N8: Subject To | O8: payment Terms | P8: Remarks
B9: VALENCIA | C9: Buenos Aires, Argentina | D9: GC | E9: 24 | F9: Via Algeciras | G9: EUR | H9: 575 | I9: 700 | J9: 675 | K9: FCR, THC origen | L9: INCL. | M9: 75 | N9: EBS;RCT;THD;DOC;T3;ETS;TCM | O9: ONLY PREPAID
B10: VALENCIA | C10: Itajai, Santa Cararina, Brazil | D10: GC | E10: 39 | F10: Via Algeciras | G10: EUR | H10: 875 | I10: 925 | J10: 925 | K10: FCR, THC origen | L10: INCL. | M10: =$M$9 -> 75 | N10: EBS;THD;DOC;T3;ETS;TCM | O10: ONLY PREPAID
B11: VALENCIA | C11: Paranagua, Parana, Brazil | D11: GC | E11: 20 | F11: Via Algeciras | G11: EUR | H11: 800 | I11: 825 | J11: 825 | K11: FCR, THC origen | L11: INCL. | M11: =$M$9 -> 75 | N11: =$N$10 -> EBS;THD;DOC;T3;ETS;TCM | O11: ONLY PREPAID
B12: VALENCIA | C12: Rio de Janeiro, Brazil | D12: GC | E12: 32 | F12: Via Algeciras | G12: EUR | H12: 875 | I12: 1100 | J12: 1100 | K12: FCR, THC origen | L12: INCL. | M12: =$M$9 -> 75 | N12: =$N$10 -> EBS;THD;DOC;T3;ETS;TCM | O12: ONLY PREPAID
B13: VALENCIA | C13: Santos, Sao Paulo, Brazil | D13: GC | E13: 18 | F13: Via Algeciras | G13: EUR | H13: 575 | I13: 700 | J13: 650 | K13: FCR, THC origen | L13: INCL. | M13: =$M$9 -> 75 | N13: =$N$10 -> EBS;THD;DOC;T3;ETS;TCM | O13: ONLY PREPAID
B14: VALENCIA | C14: Montevideo, Uruguay | D14: GC | E14: 23 | F14: Via Algeciras | G14: EUR | H14: 625 | I14: 700 | J14: 850 | K14: FCR, THC origen | L14: INCL. | M14: =$M$9 -> 75 | N14: =$N$10 -> EBS;THD;DOC;T3;ETS;TCM | O14: ONLY PREPAID
B15: BARCELONA | C15: Buenos Aires, Argentina | D15: GC | E15: 34 | F15: Via Algeciras | G15: EUR | H15: 700 | I15: 900 | J15: 875 | K15: FCR, THC origen | L15: INCL. | M15: =$M$9 -> 75 | N15: =$N$9 -> EBS;RCT;THD;DOC;T3;ETS;TCM | O15: ONLY PREPAID
B16: BARCELONA | C16: Itajai, Santa Cararina, Brazil | D16: GC | E16: 39 | F16: Via Algeciras | G16: EUR | H16: 1000 | I16: 1025 | J16: 1025 | K16: FCR, THC origen | L16: INCL. | M16: =$M$9 -> 75 | N16: =$N$10 -> EBS;THD;DOC;T3;ETS;TCM | O16: ONLY PREPAID
B17: BARCELONA | C17: Paranagua, Parana, Brazil | D17: GC | E17: 30 | F17: Via Algeciras | G17: EUR | H17: 1125 | I17: 1325 | J17: 1325 | K17: FCR, THC origen | L17: INCL. | M17: =$M$9 -> 75 | N17: =$N$10 -> EBS;THD;DOC;T3;ETS;TCM | O17: ONLY PREPAID
B18: BARCELONA | C18: Rio de Janeiro, Brazil | D18: GC | E18: 32 | F18: Via Algeciras | G18: EUR | H18: 1000 | I18: 1200 | J18: 1200 | K18: FCR, THC origen | L18: INCL. | M18: =$M$9 -> 75 | N18: =$N$10 -> EBS;THD;DOC;T3;ETS;TCM | O18: ONLY PREPAID
B19: BARCELONA | C19: Santos, Sao Paulo, Brazil | D19: GC | E19: 28 | F19: Via Algeciras | G19: EUR | H19: 900 | I19: 1200 | J19: 1150 | K19: FCR, THC origen | L19: INCL. | M19: =$M$9 -> 75 | N19: =$N$10 -> EBS;THD;DOC;T3;ETS;TCM | O19: ONLY PREPAID
B20: BARCELONA | C20: Montevideo, Uruguay | D20: GC | E20: 41 | F20: Via Algeciras | G20: EUR | H20: 950 | I20: 1200 | J20: 1350 | K20: FCR, THC origen | L20: INCL. | M20: =$M$9 -> 75 | N20: =$N$10 -> EBS;THD;DOC;T3;ETS;TCM | O20: ONLY PREPAID
B21: ALGECIRAS | C21: Buenos Aires, Argentina | D21: GC | E21: 18 | F21: Direct | G21: EUR | H21: 150 | I21: 200 | J21: 200 | K21: FCR, THC origen | L21: INCL. | M21: =$M$9 -> 75 | N21: =$N$9 -> EBS;RCT;THD;DOC;T3;ETS;TCM | O21: ONLY PREPAID
B22: ALGECIRAS | C22: Itajai, Santa Cararina, Brazil | D22: GC | E22: 27 | F22: Direct | G22: EUR | H22: 300 | I22: 350 | J22: 350 | K22: FCR, THC origen | L22: INCL. | M22: =$M$9 -> 75 | N22: =$N$10 -> EBS;THD;DOC;T3;ETS;TCM | O22: ONLY PREPAID
B23: ALGECIRAS | C23: Paranagua, Parana, Brazil | D23: GC | E23: 14 | F23: Direct | G23: EUR | H23: 350 | I23: 525 | J23: 375 | K23: FCR, THC origen | L23: INCL. | M23: =$M$9 -> 75 | N23: =$N$10 -> EBS;THD;DOC;T3;ETS;TCM | O23: ONLY PREPAID
B24: ALGECIRAS | C24: Rio de Janeiro, Brazil | D24: GC | E24: 26 | F24: Direct | G24: EUR | H24: 300 | I24: 350 | J24: 350 | K24: FCR, THC origen | L24: INCL. | M24: =$M$9 -> 75 | N24: =$N$10 -> EBS;THD;DOC;T3;ETS;TCM | O24: ONLY PREPAID
B25: ALGECIRAS | C25: Santos, Sao Paulo, Brazil | D25: GC | E25: 12 | F25: Direct | G25: EUR | H25: 225 | I25: 450 | J25: 275 | K25: FCR, THC origen | L25: INCL. | M25: =$M$9 -> 75 | N25: =$N$10 -> EBS;THD;DOC;T3;ETS;TCM | O25: ONLY PREPAID
B26: ALGECIRAS | C26: Montevideo, Uruguay | D26: GC | E26: 17 | F26: Direct | G26: EUR | H26: 425 | I26: 625 | J26: 450 | K26: FCR, THC origen | L26: INCL. | M26: =$M$9 -> 75 | N26: =$N$10 -> EBS;THD;DOC;T3;ETS;TCM | O26: ONLY PREPAID
B29: REMARKS
B30: a. Fletes validos para mercancia FAK. No incluye: MARMOL(Bloque)/PIELES/SCRAPS/HIGH VALUE CARGO/SECOND HAND VEHICLES
B31: b. Fletes incluyen AMS/CWC/CWX/THC/FCR y estan sujetos a THD/DOC/T3/ETS/TCM
B32: c. DG charge of EUR 250/cntr
B33: d. FCR INCLUDED
B34: e. EU ETS compliance Fee - EUR18/TEU - PREPAID
B35: f. Sujeto a los gastos de Destino
B36: g. River Plate Channel Toll (Buenos Aires): USD 175/cntr - COLLECT
B37: h. Equipmen maintenance premium(Buenos Aires): USD 30/cntr - COLLECT
B38: i. B/L - M/F Correction on AMS : EUR 50 / correction
B39: j. B/L Fee EUR 100/BL for manual submission, EUR 30/BL for submission (BKG&SI) through My OOCL Center
B40: k. Sujetos a VGM (VLC = EUR 10/cntr) - resto de puertos por cta cliente (si no consultar)
... B45: p. DG Documentation fee: Eur 40,- x ONU (maximo 3 x doc)
B46: Q. Emergency Bunker Surcharge: EUR 75/20`& EUR 150/40´ from 23/March/2026 | H46: Rule Tariff Detail
B48: All surcharges and Fees shown are maximum rates and valid untill further notice (unless specified)
B49: http://www.oocl.com/eng/resourcecenter/surcharges/pages/aetsurcharges.aspx
B50: http://www.oocl.com/eng/Pages/importantnoticeforratedocument.aspx

Sheet GASTOS FOB 251120
A1: POL: Barcelona/Valencia/Bilbao/Vigo/Algeciras | B1: EXPORT
A2: Export | B2: DRY | D2: REEFER
B3: 20'GP | C3: 40'GP/HQ | D3: 20'RF | E3: 40'RQ
A4: Manipulaciones/THC - BCN/VLC/ALG/BIO/VGO | B4: Eur 210,- x cntr DRY | D4: Eur 320,- x cntr Reefer | F4: * En caso de equipo especial extramedidas, se factura adicional de 80 EUR
A5: Documentacion/DOC (*) from 1/1/2022 | B5: Eur 100,- x BL
A6: IMO Documentation/DGF | B6: Eur 40,- x ONU (maximo 3 x doc)* | F6: * Eur 5 x ONU adicional
A7: T-3 commodity - Wharfage / WHF-WHO - BIO | B7: Eur 2,65 x ton
A8: T-3 tara - Wharfage / PDU - Bilbao | B8: Eur 2,51 | C8: Eur 5,02 | D8: Eur 2,51 | E8: Eur 5,02
A9: T-3 Simplificada - WHF - Algeciras | B9: Eur 26,55 | C9: Eur 35,78 | D9: Eur 26,55 | E9: Eur 35,78
A10: T-3 simplificada / WHF - Barcelona | B10: Eur 21,20 | C10: Eur 31,80 | D10: Eur 21,20 | E10: Eur 31,80
A11: T-3 simplificada / WHF - Valencia | B11: Eur 25,44 | C11: Eur 38,16 | D11: Eur 25,44 | E11: Eur 38,16
A12: T-3 simplificada / TPI - Vigo | B12: Eur 25,44 | C12: Eur 38,16 | D12: Eur 25,44 | E12: Eur 38,16
A13: USA/China/Japan M/F Transmission | B13: Eur 25,- x BL
A14: Amendment after transmission USA | B14: Eur 25,- x BL
A15: TERMINAL CUSTOMS MONITORING (TCM) | B15: Eur 10/cntr
A16: VALENCIA/BARCELONA: Cambio Status cntr (*) | B16: Eur 50/cntr
A17: VGM Valencia (Noatum- all cntrs will be weighted)** | B17: Eur 10,- x cntr
A18: VGM Valencia (APM Terminals) **Optional - TRUCK | B18: Eur 30.00 x cntr
A19: VGM Valencia (APM Terminals) **Optional - RAIL | B19: Eur 60.00 x cntr
A20: VGM VIGO (VGM done by TML at arrival) | B20: Eur 6,58 x cntr
A21: VGM BILBAO (VGM done by TML at arrival) | B21: Eur 10,- x cntr
A22: VGM BCN *** - opcional | B22: Eur 23.37 x cntr
A23: VGM BCN (BEST Terminals) **Optional - RAIL | B23: Eur 53.65 x cntr
A24: VGM ALGECIRAS - opcional - Solo con Carrier Haulage | B24: Eur 55,- x cntr | F24: La terminal no pesa
A25: Certificate | B25: Eur 30,- x Certificate
A26: BOOKING CANCELATION FEE (BCF) | B26: Eur 50/teu | F26: Applicable if the booking is cancelled or transfered to the next vessel 5 or less working days before the cutoff
A27: Amendment B/L after 5 days departure | B27: Eur 50,- x BL
A28: Late Pick Up Fee (1) | B28: Eur 50,- x BL
A29: Quebranto / BNK | B29: 0.01
A30: Customs movement (Posicionado en terminal) BCN - Dry | B30: Eur 76/cntr
A31: Customs movement (Posicionado en terminal) BCN - Reefer | B31: Eur 95/ cntr
A32: Customs movement (Posicionado en terminal) VLC | B32: Eur 105/cntr
A33: Customs movement (Posicionado en terminal) ALR | B33: Eur 105/cntr
A34: Customs movement (Posicionado en terminal) BIO | B34: Eur 76/cntr
A35: Customs movement (Posicionado en terminal) VIGO | B35: Eur 35/cntr
A36: Gate In/Out (puertas) BCN | B36: Eur 85/20' | D36: Eur 95/40'
A37: Gate In/Out (puertas) VLC | B37: Eur 85/20' | D37: Eur 95/40'
A38: Gate In/Out (puertas) BIO | B38: Eur 95/20' | D38: Eur 95/40'
A39: Gate In/Out (puertas) VIGO | B39: Eur 55/20' | D39: Eur 55/40'
A40: Gate In/Out (puertas) ALGECIRAS | B40: Eur 85/20' | D40: Eur 95/40'
A41: Customs Clearance | B41: Eur 50,-
A42: DAE - Green | B42: Eur 20,- x DAE
A43: DAE - Orange | B43: Eur 25,- x DAE
A44: DAE - Red | B44: Eur30,- x DAE
A45: PTI fail | D45: Eur 75,-
A46: Pre-cooling | D46: Eur 95,-
A47: Recargo mercancia caliente Valencia | D47: EUR 200 | F47: Aplicable a todas aquellas unidades cuya temperatura difiera en más de ±4 grados desde la primera lectura registrada después de su entrada en la terminal hasta el día siguiente a su entrada.
A48: Cntr pre-assignation BCN/VLC/BIO/VGO/AGR | B48: Eur 75,-
A49: Data logger, etc (MOR) | C49: Usd 300
A50: Cntr Food Grade preparation | B50: Eur 50,-
A51: Cesion Transporte en Bilbao/Vigo | B51: Eur 20,-
A52: Custom Stop (Doble parada tte.) - BCN | B52: EUR 92/cntr
A53: Custom Stop (Doble parada tte.) - ZARAGOZA | B53: EUR 60/cntr
A54: Custom Stop (Doble parada tte.) - VLC | B54: EUR 60/cntr
A55: Custom Stop (Doble parada tte.) - MADRID | B55: EUR 72/cntr
A56: Custom Stop (Doble parada tte.) - ALG | B56: EUR 60/cntr
A57: Custom Stop (Doble parada tte.) - BIO | B57: EUR 92/cntr
A58: Custom Stop (Doble parada tte.) - VIGO | B58: EUR 51/cntr
A60: (*) Booking by OOCL WEB | D60: Eur 40,- x bl
A61: (*) Booking & Shipping Instructions BY OOCL WEB | D61: Eur 30,- x bl
A63: (1) Late Pick up Fee | B63: Si el BL no se retira antes de 5 dias laborables a la salida del buque
A64: (***) VGM BCN: | B64: If done by customer VGM must be transmitted within the 24 hrs of cntr arrival. If not done in time there will be one horizontal movement applied by terminal Eur 50,- x cntr
A65: (**) VGM VLC: | B65: NOATUM - Done always by terminal, so applicable TO ALL cntrs moved via Valencia port (Noatum Terminal)
A66: (*) Cambio Status cntr (VLC-BCN) | B66: Cambio destino/Cambio Buque/Rolling falta despacho - Una vez el cntr esta dentro de terminal
A69: DEMURRAGES/DETENTIONS/QUAY RENT/REEFER MONITORING from 20/November/2025
A71: Outbound Combined Demurrage and Detention (DD2in1)
A72: Trade | B72: Cargo Nature/Equipment Type | C72: Free Time | D72: Day Range | E72: 20' | F72: 40' | G72: 40'HQ | H72: Currency
A73: All trade | B73: Dry Container | C73: 12C | D73: 1--5 | E73: 30 | F73: 42 | G73: 42 | H73: EUR
A74: All trade | B74: Dry Container | D74: Thereafter | E74: 52 | F74: 85 | G74: 85 | H74: EUR
A75: All trade | B75: Special Equipment | C75: 12C | D75: 1--7 | E75: 45 | F75: 60 | G75: 60 | H75: EUR
A76: All trade | B76: Special Equipment | D76: Thereafter | E76: 55 | F76: 85 | G76: 85 | H76: EUR
A77: All trade | B77: Reefer Container | C77: 6C | D77: 1--2 | E77: 35 | F77: - | G77: 55 | H77: EUR
A78: All trade | B78: Reefer Container | D78: 3--7 | E78: 65 | F78: - | G78: 75 | H78: EUR
A79: All trade | B79: Reefer Container | D79: Thereafter | E79: 95 | F79: - | G79: 105 | H79: EUR
A80: All trade | B80: Non-operating Reefer Container | C80: 12C | D80: 1--2 | E80: 35 | F80: - | G80: 55 | H80: EUR
A81: All trade | B81: Non-operating Reefer Container | D81: 3--7 | E81: 65 | F81: 75 | G81: 70 | H81: EUR
A82: All trade | B82: Non-operating Reefer Container | D82: Thereafter | E82: 95 | F82: - | G82: 105 | H82: EUR
A84: Outbound Combined Demurrage and Detention (DD2in1) Calculation shall commerce on the same day of empty gate out and end at 23:59 on cargo cutoff day.
A86: Reefer Monitoring
A87: Trade | B87: Cargo Nature/Equipment Type | C87: Free Time | D87: Day Range | E87: 20' | F87: 40' | G87: 40'HQ | H87: Currency
A88: All trade/Barcelona/Valencia/Algeciras/Vigo | B88: Reefer Container | C88: 4C | D88: Thereafter | E88: 60 | F88: - | G88: 60 | H88: EUR
A89: All trade/ Bilbao | B89: Reefer Container | C89: 3C | D89: Thereafter | E89: 60 | F89: - | G89: 60 | H89: EUR
A92: Outbound Quay Rent/Storages at terminal
A93: Port | B93: Cargo Nature/Equipment Type | C93: Free Time | D93: Day Range | E93: 20' | F93: 40' | G93: 40'HQ | H93: Currency
A94: Castello de la Plana | B94: All | C94: 10C | D94: 1--5 | E94: 3 | F94: 5 | G94: 5 | H94: EUR
B95: All | D95: Thereafter | E95: 5 | F95: 9 | G95: 9 | H95: EUR
A96: Barcelona | B96: All | C96: 7C | D96: 1--7 | E96: 5 | F96: 10 | G96: 10 | H96: EUR
B97: All | D97: Thereafter | E97: 40 | F97: 80 | G97: 80 | H97: EUR
A98: Bilbao | B98: All | C98: 4C | D98: Thereafter | E98: 2 | F98: 4 | G98: 4 | H98: EUR
A99: Valencia | B99: All | C99: 4C | D99: 1--3 | E99: 2 | F99: 4 | G99: 4 | H99: EUR
B100: All | D100: 4--14 | E100: 4 | F100: 8 | G100: 8 | H100: EUR
B101: All | D101: 15--26 | E101: 10 | F101: 20 | G101: 20 | H101: EUR
B102: All | D102: Thereafter | E102: 30 | F102: 60 | G102: 60 | H102: EUR
A103: Vigo | B103: All | C103: 5C | D103: 1--9 | E103: 1 | F103: 2 | G103: 2 | H103: EUR
B104: All | D104: 10--25 | E104: 2 | F104: 4 | G104: 4 | H104: EUR
B105: All | D105: Thereafter | E105: 4 | F105: 8 | G105: 8 | H105: EUR
A106: Algeciras | B106: All | C106: 5C | D106: 1--7 | E106: 2 | F106: 4 | G106: 4 | H106: EUR
B107: All | D107: 8--13 | E107: 3 | F107: 6 | G107: 6 | H107: EUR
B108: All | D108: Thereafter | E108: 4 | F108: 8 | G108: 8 | H108: EUR
A110: Outbound Quay Rent Calculation shall commence at 00:00am on the first calendar day after full gate in and end at 23:59 on cargo cutoff day
